jk_appmonitoring
