Metadata-Version: 2.1
Name: jk-appmonitoring
Version: 0.2021.1.19
Summary: This Python module contains components for analyzing the use of system resources by processes. It covers two use cases: a) monitoring other processes and b) monitoring one's own process.
Home-page: UNKNOWN
Author: Jürgen Knauth
Author-email: pubsrc@binary-overflow.de
License: Apache2
Keywords: ...
Platform: UNKNOWN
Classifier: Development Status :: 3 - Alpha
Classifier: License :: OSI Approved :: Apache Software License
Classifier: Programming Language :: Python :: 3
